setup.py
ai_utils/__init__.py
ai_utils/core.py
sree_ai_utils_v1.egg-info/PKG-INFO
sree_ai_utils_v1.egg-info/SOURCES.txt
sree_ai_utils_v1.egg-info/dependency_links.txt
sree_ai_utils_v1.egg-info/requires.txt
sree_ai_utils_v1.egg-info/top_level.txt