Metadata-Version: 2.4
Name: sree_ai_utils_v1
Version: 0.2
Summary: A simple AI helper library for Project 3
Author: Sreeraj
Requires-Dist: google-generativeai
Requires-Dist: flask
Dynamic: author
Dynamic: requires-dist
Dynamic: summary
